{
  "meta": {
    "repo": "damdravic/AxmCarService-FS",
    "stage": "J17->J21",
    "family": null,
    "sha_from": "0027445db7f07b69075cf4cc0e23e039a36ea54d",
    "sha_to": "fe07e1db073e646fa8e33bf1c22b3cf16a2856ab"
  },
  "by_file": {
    "AxmCarService/src/main/java/com/example/AxmCarService/AxmCarServiceApplication.java": [],
    "AxmCarService/pom.xml": [
      {
        "kind": "bump_parent_version",
        "general_idea": "Upgrade Spring Boot parent from 3.1.2 to 3.4.2 to align with Java 21 support and latest framework features.",
        "human_impl": "<version>3.4.2</version>",
        "bucket": "breaking"
      },
      {
        "kind": "set_java_version",
        "general_idea": "Update the project's Java version property from 17 to 21 to target the new JDK.",
        "human_impl": "<java.version>21</java.version>",
        "bucket": "breaking"
      },
      {
        "kind": "change_packaging",
        "general_idea": "Change the project packaging type to WAR to support deployment in external servlet containers.",
        "human_impl": "<packaging>war</packaging>",
        "bucket": "polishment"
      },
      {
        "kind": "add_dependency",
        "general_idea": "Add spring-jdbc dependency for direct JDBC access capabilities.",
        "human_impl": "<artifactId>spring-jdbc</artifactId>",
        "bucket": "polishment"
      },
      {
        "kind": "add_dependency",
        "general_idea": "Add jakarta.servlet-api dependency to explicitly manage servlet API version.",
        "human_impl": "<artifactId>jakarta.servlet-api</artifactId>",
        "bucket": "polishment"
      },
      {
        "kind": "add_dependency",
        "general_idea": "Re-add spring-boot-starter-data-jpa with an explicit version, previously removed or managed differently.",
        "human_impl": "<artifactId>spring-boot-starter-data-jpa</artifactId>",
        "bucket": "polishment"
      },
      {
        "kind": "add_dependency",
        "general_idea": "Add spring-boot-starter-mail dependency to enable email sending functionality.",
        "human_impl": "<artifactId>spring-boot-starter-mail</artifactId>",
        "bucket": "polishment"
      },
      {
        "kind": "add_dependency",
        "general_idea": "Add commons-lang3 dependency for utility classes.",
        "human_impl": "<artifactId>commons-lang3</artifactId>",
        "bucket": "polishment"
      },
      {
        "kind": "add_dependency",
        "general_idea": "Add jakarta.mail dependency for JavaMail API support.",
        "human_impl": "<artifactId>jakarta.mail</artifactId>",
        "bucket": "polishment"
      },
      {
        "kind": "add_dependency",
        "general_idea": "Add java-jwt dependency for JWT token handling.",
        "human_impl": "<artifactId>java-jwt</artifactId>",
        "bucket": "polishment"
      },
      {
        "kind": "add_dependency",
        "general_idea": "Add jakarta.validation-api dependency for bean validation support.",
        "human_impl": "<artifactId>jakarta.validation-api</artifactId>",
        "bucket": "polishment"
      },
      {
        "kind": "add_build_profile",
        "general_idea": "Add Maven profiles for dev and prod environments to manage active Spring profiles.",
        "human_impl": "<profiles>...</profiles>",
        "bucket": "polishment"
      },
      {
        "kind": "fix_plugin_config",
        "general_idea": "Correct the groupId typo in the maven-shade-plugin exclusion for Lombok.",
        "human_impl": "<groupId>org.project-lombok</groupId>",
        "bucket": "polishment"
      },
      {
        "kind": "add_plugin",
        "general_idea": "Add maven-compiler-plugin configuration, though it sets source/target to 17 which conflicts with the java.version property.",
        "human_impl": "<artifactId>maven-compiler-plugin</artifactId>",
        "bucket": "polishment"
      },
      {
        "kind": "add_plugin",
        "general_idea": "Add maven-war-plugin to support the new WAR packaging type.",
        "human_impl": "<artifactId>maven-war-plugin</artifactId>",
        "bucket": "polishment"
      }
    ],
    ".idea/compiler.xml": [
      {
        "kind": "rename_module",
        "general_idea": "Update the module name in IntelliJ compiler configuration from AxmCarService to AnaximStore to reflect the project rename.",
        "human_impl": "<module name=\"AnaximStore\" />",
        "bucket": "polishment"
      }
    ],
    ".idea/modules.xml": [
      {
        "kind": "rename_module",
        "general_idea": "Rename the IntelliJ IDEA module references from 'AxmCarService' to 'AnaximStore' to reflect the project rebranding.",
        "human_impl": "Changed fileurl and filepath attributes in .idea/modules.xml from AxmCarService to AnaximStore",
        "bucket": "polishment"
      }
    ],
    "AxmCarService/src/main/resources/application.yml": [
      {
        "kind": "externalize_db_config",
        "general_idea": "Removed hardcoded database connection details to support environment-specific configuration profiles.",
        "human_impl": "Removed spring.datasource.url, username, password, and driver properties.",
        "bucket": "polishment"
      },
      {
        "kind": "externalize_jpa_config",
        "general_idea": "Removed hardcoded JPA and Hibernate settings to allow profile-based database dialect and DDL configuration.",
        "human_impl": "Removed spring.jpa.database-platform, hibernate.dialect, and ddl-auto properties.",
        "bucket": "polishment"
      },
      {
        "kind": "enable_profile_activation",
        "general_idea": "Configured the application to activate a specific profile (dev) instead of using default global settings.",
        "human_impl": "Added spring.profiles.active: dev.",
        "bucket": "polishment"
      },
      {
        "kind": "remove_sql_init",
        "general_idea": "Disabled automatic SQL initialization on startup, likely moving schema management to Flyway/Liquibase or profile-specific scripts.",
        "human_impl": "Removed spring.sql.init.mode: always.",
        "bucket": "polishment"
      }
    ],
    "AxmCarService/src/main/resources/schema.sql": [
      {
        "kind": "disable_drop_statements",
        "general_idea": "Commented out DROP TABLE statements to prevent data loss during schema initialization.",
        "human_impl": "--DROP TABLE IF EXISTS ...",
        "bucket": "polishment"
      },
      {
        "kind": "add_if_not_exists_users",
        "general_idea": "Added IF NOT EXISTS clause to users table creation for idempotency.",
        "human_impl": "CREATE TABLE IF NOT EXISTS users",
        "bucket": "polishment"
      },
      {
        "kind": "add_workshop_table",
        "general_idea": "Created new workshop table to store workshop details.",
        "human_impl": "CREATE TABLE IF NOT EXISTS workshop",
        "bucket": "polishment"
      },
      {
        "kind": "add_vehicle_table",
        "general_idea": "Created new vehicle table to store vehicle details.",
        "human_impl": "CREATE TABLE IF NOT EXISTS vehicle",
        "bucket": "polishment"
      },
      {
        "kind": "add_repair_order_table",
        "general_idea": "Created new repair_order table to manage repair jobs.",
        "human_impl": "CREATE TABLE IF NOT EXISTS repair_order",
        "bucket": "polishment"
      },
      {
        "kind": "add_parts_table",
        "general_idea": "Created new parts table to store inventory parts.",
        "human_impl": "CREATE TABLE IF NOT EXISTS parts",
        "bucket": "polishment"
      },
      {
        "kind": "add_technician_table",
        "general_idea": "Created new technician table to store technician profiles.",
        "human_impl": "CREATE TABLE IF NOT EXISTS technician",
        "bucket": "polishment"
      },
      {
        "kind": "add_customer_table",
        "general_idea": "Created new customer table to store customer information.",
        "human_impl": "CREATE TABLE IF NOT EXISTS customer",
        "bucket": "polishment"
      },
      {
        "kind": "add_labor_table",
        "general_idea": "Created new labor table to store labor service types.",
        "human_impl": "CREATE TABLE IF NOT EXISTS labor",
        "bucket": "polishment"
      },
      {
        "kind": "add_repair_order_part_table",
        "general_idea": "Created new repair_order_part junction table for many-to-many relationship.",
        "human_impl": "CREATE TABLE IF NOT EXISTS repair_order_part",
        "bucket": "polishment"
      },
      {
        "kind": "add_repair_order_labor_table",
        "general_idea": "Created new repair_order_labor junction table for many-to-many relationship.",
        "human_impl": "CREATE TABLE IF NOT EXISTS repair_order_labor",
        "bucket": "polishment"
      },
      {
        "kind": "add_if_not_exists_roles",
        "general_idea": "Added IF NOT EXISTS clause to roles table creation for idempotency.",
        "human_impl": "CREATE TABLE IF NOT EXISTS roles",
        "bucket": "polishment"
      },
      {
        "kind": "add_if_not_exists_user_roles",
        "general_idea": "Added IF NOT EXISTS clause to user_roles table creation for idempotency.",
        "human_impl": "CREATE TABLE IF NOT EXISTS user_roles",
        "bucket": "polishment"
      },
      {
        "kind": "fix_user_roles_fk_case",
        "general_idea": "Fixed foreign key references in user_roles to use lowercase table names.",
        "human_impl": "REFERENCES users(user_id) ... REFERENCES roles(role_id)",
        "bucket": "polishment"
      },
      {
        "kind": "add_if_not_exists_events",
        "general_idea": "Added IF NOT EXISTS clause to events table creation for idempotency.",
        "human_impl": "CREATE TABLE IF NOT EXISTS events",
        "bucket": "polishment"
      },
      {
        "kind": "add_if_not_exists_user_events",
        "general_idea": "Added IF NOT EXISTS clause to user_events table creation for idempotency.",
        "human_impl": "CREATE TABLE IF NOT EXISTS user_events",
        "bucket": "polishment"
      },
      {
        "kind": "add_if_not_exists_account_verifications",
        "general_idea": "Added IF NOT EXISTS clause to account_verifications table creation for idempotency.",
        "human_impl": "CREATE TABLE IF NOT EXISTS account_verifications",
        "bucket": "polishment"
      },
      {
        "kind": "fix_account_verification_typo",
        "general_idea": "Fixed typo in constraint name from Veriffication to Verification.",
        "human_impl": "CONSTRAINT UQ_AccountVerification_User_Id",
        "bucket": "polishment"
      },
      {
        "kind": "add_if_not_exists_reset_pass_verifications",
        "general_idea": "Added IF NOT EXISTS clause to reset_pass_verifications table creation for idempotency.",
        "human_impl": "CREATE TABLE IF NOT EXISTS reset_pass_verifications",
        "bucket": "polishment"
      },
      {
        "kind": "fix_reset_pass_column_typo",
        "general_idea": "Fixed typo in column name from expirtation_date to expiration_date.",
        "human_impl": "expiration_date DATETIME DEFAULT NULL",
        "bucket": "polishment"
      },
      {
        "kind": "fix_reset_pass_constraint_typo",
        "general_idea": "Fixed typo in constraint name from Veriffication to Verification.",
        "human_impl": "CONSTRAINT UQ_ResetPassVerification_User_Id",
        "bucket": "polishment"
      },
      {
        "kind": "add_if_not_exists_two_factor_verifications",
        "general_idea": "Added IF NOT EXISTS clause to two_factor_verifications table creation for idempotency.",
        "human_impl": "CREATE TABLE IF NOT EXISTS two_factor_verifications",
        "bucket": "polishment"
      },
      {
        "kind": "fix_two_factor_column_typo",
        "general_idea": "Fixed typo in column name from expirtatio_date to expiration_date.",
        "human_impl": "expiration_date DATETIME DEFAULT NULL",
        "bucket": "polishment"
      },
      {
        "kind": "fix_two_factor_constraint_typo",
        "general_idea": "Fixed typo in constraint name from Veriffication to Verification.",
        "human_impl": "CONSTRAINT UQ_TwoFactorVerification_User_Id",
        "bucket": "polishment"
      }
    ]
  }
}