{
  "idiomatic_java21": 4,
  "antipattern_clearance": 4,
  "diff_coherence": 4,
  "overall": 4,
  "justification": "The diff correctly migrates from Hibernate 5 (javax.persistence) to Hibernate 6 (jakarta.persistence) and updates the Maven compiler to use the `release` flag. It also applies Java 21 idioms like pattern matching for `instanceof` and `List.getFirst()`. However, it misses some opportunities for modernization (e.g., `String.formatted` is used in one place but `String.format` remains elsewhere, and `Runtime.exec` is updated but could be cleaner). The import cleanup is thorough but slightly inconsistent in some files."
}