{
  "meta": {
    "repo": "jhipster/jhipster-sample-app-react",
    "stage": "J11->J17",
    "family": "hibernate-5",
    "sha_from": "f8906cc132828d9158658f47ac954bb8c1e3e94f",
    "sha_to": "3525bc4106eeffcb1f13675603aac4da64c492bf"
  },
  "by_file": {
    ".mvn/wrapper/MavenWrapperDownloader.java": [
      {
        "general_idea": "Update Apache License URL from http to https for security compliance.",
        "why_exists": "",
        "before": "http://www.apache.org/licenses/LICENSE-2.0",
        "after": "https://www.apache.org/licenses/LICENSE-2.0",
        "kind": "update_license_url",
        "bucket": "polishment"
      },
      {
        "general_idea": "Reorder import statements to follow standard convention (java.io before java.net).",
        "why_exists": "",
        "before": "import java.net.*;\nimport java.io.*;",
        "after": "import java.io.*;\nimport java.net.*;",
        "kind": "reorder_imports",
        "bucket": "polishment"
      },
      {
        "general_idea": "Reformat string concatenation in DEFAULT_DOWNLOAD_URL to single line.",
        "why_exists": "",
        "before": "private static final String DEFAULT_DOWNLOAD_URL = \"https://repo.maven.apache.org/maven2/io/takari/maven-wrapper/\"\n        + WRAPPER_VERSION + \"/maven-wrapper-\" + WRAPPER_VERSION + \".jar\";",
        "after": "private static final String DEFAULT_DOWNLOAD_URL =\n        \"https://repo.maven.apache.org/maven2/io/takari/maven-wrapper/\" + WRAPPER_VERSION + \"/maven-wrapper-\" + WRAPPER_VERSION + \".jar\";",
        "kind": "reformat_string_concat",
        "bucket": "polishment"
      },
      {
        "general_idea": "Reformat constant string assignments to single line.",
        "why_exists": "",
        "before": "private static final String MAVEN_WRAPPER_PROPERTIES_PATH =\n            \".mvn/wrapper/maven-wrapper.properties\";",
        "after": "private static final String MAVEN_WRAPPER_PROPERTIES_PATH = \".mvn/wrapper/maven-wrapper.properties\";",
        "kind": "reformat_constant",
        "bucket": "polishment"
      },
      {
        "general_idea": "Reformat constant string assignments to single line.",
        "why_exists": "",
        "before": "private static final String MAVEN_WRAPPER_JAR_PATH =\n            \".mvn/wrapper/maven-wrapper.jar\";",
        "after": "private static final String MAVEN_WRAPPER_JAR_PATH = \".mvn/wrapper/maven-wrapper.jar\";",
        "kind": "reformat_constant",
        "bucket": "polishment"
      },
      {
        "general_idea": "Add space after 'if' keyword for consistent formatting.",
        "why_exists": "",
        "before": "if(mavenWrapperPropertyFile.exists()) {",
        "after": "if (mavenWrapperPropertyFile.exists()) {",
        "kind": "fix_spacing",
        "bucket": "polishment"
      },
      {
        "general_idea": "Add space after 'if' keyword for consistent formatting.",
        "why_exists": "",
        "before": "if(mavenWrapperPropertyFileInputStream != null) {",
        "after": "if (mavenWrapperPropertyFileInputStream != null) {",
        "kind": "fix_spacing",
        "bucket": "polishment"
      },
      {
        "general_idea": "Add space after 'if' keyword and reformat nested if block.",
        "why_exists": "",
        "before": "if(!outputFile.getParentFile().exists()) {\n            if(!outputFile.getParentFile().mkdirs()) {",
        "after": "if (!outputFile.getParentFile().exists()) {\n            if (!outputFile.getParentFile().mkdirs()) {",
        "kind": "fix_spacing",
        "bucket": "polishment"
      },
      {
        "general_idea": "Reformat System.out.println call to single line.",
        "why_exists": "",
        "before": "System.out.println(\n                        \"- ERROR creating output directory '\" + outputFile.getParentFile().getAbsolutePath() + \"'\");",
        "after": "System.out.println(\"- ERROR creating output directory '\" + outputFile.getParentFile().getAbsolutePath() + \"'\");",
        "kind": "reformat_method_call",
        "bucket": "polishment"
      },
      {
        "general_idea": "Reformat anonymous Authenticator class instantiation for better readability.",
        "why_exists": "",
        "before": "Authenticator.setDefault(new Authenticator() {\n                @Override\n                protected PasswordAuthentication getPasswordAuthentication() {\n                    return new PasswordAuthentication(username, password);\n                }\n            });",
        "after": "Authenticator.setDefault(\n                new Authenticator() {\n                    @Override\n                    protected PasswordAuthentication getPasswordAuthentication() {\n                        return new PasswordAuthentication(username, password);\n                    }\n                }\n            );",
        "kind": "reformat_anonymous_class",
        "bucket": "polishment"
      },
      {
        "general_idea": "Remove trailing whitespace at end of file.",
        "why_exists": "",
        "before": "\n}",
        "after": "}",
        "kind": "remove_trailing_whitespace",
        "bucket": "polishment"
      }
    ],
    "src/main/java/io/github/jhipster/sample/GeneratedByJHipster.java": [
      {
        "general_idea": "Migrate the Generated annotation import from javax.annotation to jakarta.annotation to align with Jakarta EE namespace changes.",
        "why_exists": "The javax.annotation package is removed or deprecated in newer Jakarta EE versions; using it causes compilation errors or classpath conflicts when the project targets Jakarta EE 9+ artifacts.",
        "before": "import javax.annotation.Generated;",
        "after": "import jakarta.annotation.Generated;",
        "kind": "javax_to_jakarta_import",
        "bucket": "breaking"
      },
      {
        "general_idea": "Update the version string in the Generated annotation comment to reflect the current JHipster version.",
        "why_exists": "",
        "before": "@Generated(value = \"JHipster\", comments = \"Generated by JHipster 7.0.0-beta.0\")",
        "after": "@Generated(value = \"JHipster\", comments = \"Generated by JHipster 7.9.3\")",
        "kind": "update_version_comment",
        "bucket": "polishment"
      }
    ],
    "src/main/java/io/github/jhipster/sample/JhipsterSampleApplicationReactApp.java": [
      {
        "general_idea": "Replace javax.annotation with jakarta.annotation to align with Jakarta EE namespace changes in Spring Boot 3.",
        "why_exists": "javax.annotation package is removed in Java 9+ and not present in Spring Boot 3 dependencies; code fails to compile with 'package javax.annotation does not exist'.",
        "before": "import javax.annotation.PostConstruct;",
        "after": "import jakarta.annotation.PostConstruct;",
        "kind": "jakarta_namespace_migration",
        "bucket": "breaking"
      },
      {
        "general_idea": "Adopt Java 17 text blocks for multi-line string literals to improve readability.",
        "why_exists": "",
        "before": "\"\\n----------------------------------------------------------\\n\\t\" +\n            \"Application '{}' is running! Access URLs:\\n\\t\" +\n            \"Local: \\t\\t{}://localhost:{}{}\\n\\t\" +\n            \"External: \\t{}://{}:{}{}\\n\\t\" +\n            \"Profile(s): \\t{}\\n----------------------------------------------------------\"",
        "after": "CRLFLogConverter.CRLF_SAFE_MARKER,\n            \"\"\"\n\n                ----------------------------------------------------------\n                \\tApplication '{}' is running! Access URLs:\n                \\tLocal: \\t\\t{}://localhost:{}{}\n                \\tExternal: \\t{}://{}:{}{}\n                \\tProfile(s): \\t{}\n                ----------------------------------------------------------\"\"\"",
        "kind": "text_block_migration",
        "bucket": "polishment"
      },
      {
        "general_idea": "Add CRLFLogConverter marker to log statement to ensure log lines are not split by logback converters.",
        "why_exists": "",
        "before": "log.info(\n            \"\\n----------------------------------------------------------...",
        "after": "log.info(\n            CRLFLogConverter.CRLF_SAFE_MARKER,\n            \"\"\"\n\n                ----------------------------------------------------------...",
        "kind": "log_formatting_fix",
        "bucket": "polishment"
      },
      {
        "general_idea": "Import CRLFLogConverter class used in the logging statement.",
        "why_exists": "",
        "before": "",
        "after": "import io.github.jhipster.sample.config.CRLFLogConverter;",
        "kind": "add_import",
        "bucket": "polishment"
      },
      {
        "general_idea": "Handle empty active profiles by falling back to default profiles to ensure the log message always displays profile information.",
        "why_exists": "",
        "before": "env.getActiveProfiles()",
        "after": "env.getActiveProfiles().length == 0 ? env.getDefaultProfiles() : env.getActiveProfiles()",
        "kind": "logic_refinement",
        "bucket": "polishment"
      }
    ],
    "src/main/java/io/github/jhipster/sample/aop/logging/LoggingAspect.java": [],
    "src/main/java/io/github/jhipster/sample/config/ApplicationProperties.java": [],
    "src/main/java/io/github/jhipster/sample/config/AsyncConfiguration.java": [
      {
        "general_idea": "Add a Spring profile condition to exclude the AsyncConfiguration bean from loading during specific test profiles.",
        "why_exists": "",
        "before": "@Configuration\n@EnableAsync\n@EnableScheduling\npublic class AsyncConfiguration implements AsyncConfigurer {",
        "after": "@Configuration\n@EnableAsync\n@EnableScheduling\n@Profile(\"!testdev & !testprod\")\npublic class AsyncConfiguration implements AsyncConfigurer {",
        "kind": "add_profile_annotation",
        "bucket": "polishment"
      }
    ],
    "src/main/java/io/github/jhipster/sample/config/DatabaseConfiguration.java": [
      {
        "general_idea": "Wrap single string argument in array syntax for @EnableJpaRepositories annotation.",
        "why_exists": "",
        "before": "@EnableJpaRepositories(\"io.github.jhipster.sample.repository\")",
        "after": "@EnableJpaRepositories({ \"io.github.jhipster.sample.repository\" })",
        "kind": "annotation_syntax_normalization",
        "bucket": "polishment"
      }
    ],
    "src/main/java/io/github/jhipster/sample/config/JacksonConfiguration.java": [
      {
        "general_idea": "Replace the Hibernate 5 Jackson module with its Jakarta EE namespace variant to support the migration from javax to jakarta packages.",
        "why_exists": "The original Hibernate5Module relies on javax.persistence classes which are removed or relocated in Jakarta EE environments; using the non-Jakarta module causes ClassNotFoundException or NoClassDefFoundError at runtime on JDK 17 with Jakarta dependencies.",
        "before": "import com.fasterxml.jackson.datatype.hibernate5.Hibernate5Module;\n...\npublic Hibernate5Module hibernate5Module() {\n    return new Hibernate5Module();\n}",
        "after": "import com.fasterxml.jackson.datatype.hibernate5.jakarta.Hibernate5JakartaModule;\n...\npublic Hibernate5JakartaModule hibernate5Module() {\n    return new Hibernate5JakartaModule();\n}",
        "kind": "replace_hibernate_module_with_jakarta_variant",
        "bucket": "breaking"
      },
      {
        "general_idea": "Remove Zalando Problem modules from Jackson configuration as they are no longer required or compatible with the current stack.",
        "why_exists": "",
        "before": "import org.zalando.problem.ProblemModule;\nimport org.zalando.problem.violations.ConstraintViolationProblemModule;\n...\n@Bean\npublic ProblemModule problemModule() {\n    return new ProblemModule();\n}\n@Bean\npublic ConstraintViolationProblemModule constraintViolationProblemModule() {\n    return new ConstraintViolationProblemModule();\n}",
        "after": "",
        "kind": "remove_zalando_problem_modules",
        "bucket": "polishment"
      }
    ],
    "src/main/java/io/github/jhipster/sample/config/LiquibaseConfiguration.java": [
      {
        "general_idea": "Reorder method parameters to place the annotated ObjectProvider after the plain LiquibaseProperties bean.",
        "why_exists": "",
        "before": "@LiquibaseDataSource ObjectProvider<DataSource> liquibaseDataSource,\n        LiquibaseProperties liquibaseProperties,",
        "after": "LiquibaseProperties liquibaseProperties,\n        @LiquibaseDataSource ObjectProvider<DataSource> liquibaseDataSource,",
        "kind": "reorder_method_parameters",
        "bucket": "polishment"
      },
      {
        "general_idea": "Replace deprecated setLabels method with setLabelFilter to align with updated Spring Boot LiquibaseProperties API.",
        "why_exists": "The method setLabels(String) was removed or deprecated in favor of setLabelFilter(String) in newer Spring Boot versions; calling the old method causes a compile error.",
        "before": "liquibase.setLabels(liquibaseProperties.getLabels());",
        "after": "liquibase.setLabelFilter(liquibaseProperties.getLabelFilter());",
        "kind": "update_deprecated_api_call",
        "bucket": "breaking"
      }
    ],
    "src/main/java/io/github/jhipster/sample/config/SecurityConfiguration.java": [
      {
        "general_idea": "Replace deprecated WebSecurityConfigurerAdapter with SecurityFilterChain bean to comply with Spring Security 5.7+ API changes.",
        "why_exists": "WebSecurityConfigurerAdapter is deprecated in Spring Security 5.7 and removed in Spring Security 6.0; extending it causes compilation errors or severe deprecation warnings on modern Spring Boot versions.",
        "before": "public class SecurityConfiguration extends WebSecurityConfigurerAdapter",
        "after": "public class SecurityConfiguration",
        "kind": "replace_deprecated_adapter",
        "bucket": "breaking"
      },
      {
        "general_idea": "Replace deprecated @EnableGlobalMethodSecurity with @EnableMethodSecurity to align with Spring Security 6.0 method security configuration.",
        "why_exists": "@EnableGlobalMethodSecurity is removed in Spring Security 6.0; using it results in a compilation error.",
        "before": "@EnableGlobalMethodSecurity(prePostEnabled = true, securedEnabled = true)",
        "after": "@EnableMethodSecurity(securedEnabled = true)",
        "kind": "replace_deprecated_annotation",
        "bucket": "breaking"
      },
      {
        "general_idea": "Migrate request authorization from authorizeRequests().antMatchers() to authorizeHttpRequests().requestMatchers() to use the new matcher API.",
        "why_exists": "authorizeRequests() and antMatchers() are removed in Spring Security 6.0; using them causes compilation errors.",
        "before": ".authorizeRequests().antMatchers(...)",
        "after": ".authorizeHttpRequests(authz -> authz.requestMatchers(...))",
        "kind": "migrate_authorization_api",
        "bucket": "breaking"
      },
      {
        "general_idea": "Migrate header configuration from fluent DSL to lambda-based configuration to comply with Spring Security 6.0 API.",
        "why_exists": "The old fluent header configuration methods (e.g., .contentSecurityPolicy(String)) are removed in Spring Security 6.0; using them causes compilation errors.",
        "before": ".headers().contentSecurityPolicy(\"...\").referrerPolicy(...).featurePolicy(...).frameOptions().deny()",
        "after": ".headers(headers -> headers.contentSecurityPolicy(csp -> ...).referrerPolicy(...).permissionsPolicy(...).frameOptions(...))",
        "kind": "migrate_header_api",
        "bucket": "breaking"
      },
      {
        "general_idea": "Replace custom JWT configuration with standard OAuth2 Resource Server JWT configuration.",
        "why_exists": "The custom JWTConfigurer approach is incompatible with the new SecurityFilterChain model and Spring Security 6.0's preferred OAuth2 resource server integration.",
        "before": ".apply(securityConfigurerAdapter())",
        "after": ".oauth2ResourceServer(oauth2 -> oauth2.jwt())",
        "kind": "migrate_jwt_config",
        "bucket": "breaking"
      },
      {
        "general_idea": "Replace custom SecurityProblemSupport exception handling with standard BearerTokenAuthenticationEntryPoint and BearerTokenAccessDeniedHandler.",
        "why_exists": "The old exception handling configuration is incompatible with the new SecurityFilterChain model and OAuth2 resource server setup.",
        "before": ".exceptionHandling().authenticationEntryPoint(problemSupport).accessDeniedHandler(problemSupport)",
        "after": ".exceptionHandling(exceptions -> exceptions.authenticationEntryPoint(new BearerTokenAuthenticationEntryPoint()).accessDeniedHandler(new BearerTokenAccessDeniedHandler()))",
        "kind": "migrate_exception_handling",
        "bucket": "breaking"
      },
      {
        "general_idea": "Remove WebSecurity configuration for ignoring static resources as it is no longer needed or supported in the same way.",
        "why_exists": "The configure(WebSecurity web) method is not used in the new SecurityFilterChain bean model; static resources are handled via permitAll in authorizeHttpRequests.",
        "before": "public void configure(WebSecurity web) { web.ignoring().antMatchers(...); }",
        "after": "",
        "kind": "remove_web_security_config",
        "bucket": "breaking"
      },
      {
        "general_idea": "Update CSRF configuration to use the new lambda-based API and ignore specific request matchers.",
        "why_exists": "The old CSRF configuration API is removed in Spring Security 6.0; using it causes compilation errors.",
        "before": ".csrf().disable()",
        "after": ".csrf(csrf -> csrf.ignoringRequestMatchers(\"/h2-console/**\").disable())",
        "kind": "migrate_csrf_api",
        "bucket": "breaking"
      },
      {
        "general_idea": "Replace CorsFilter injection with SpaWebFilter for handling SPA routing and CORS.",
        "why_exists": "The old CorsFilter injection is incompatible with the new SecurityFilterChain model and the application's new SPA handling strategy.",
        "before": ".addFilterBefore(corsFilter, UsernamePasswordAuthenticationFilter.class)",
        "after": ".addFilterAfter(new SpaWebFilter(), BasicAuthenticationFilter.class)",
        "kind": "replace_cors_filter",
        "bucket": "breaking"
      },
      {
        "general_idea": "Update session management configuration to use the new lambda-based API.",
        "why_exists": "The old session management API is removed in Spring Security 6.0; using it causes compilation errors.",
        "before": ".sessionManagement().sessionCreationPolicy(SessionCreationPolicy.STATELESS)",
        "after": ".sessionManagement(session -> session.sessionCreationPolicy(SessionCreationPolicy.STATELESS))",
        "kind": "migrate_session_api",
        "bucket": "breaking"
      },
      {
        "general_idea": "Remove unused imports related to the old security configuration.",
        "why_exists": "Unused imports cause compilation warnings or errors in strict build environments.",
        "before": "import org.springframework.security.config.annotation.web.configuration.WebSecurityConfigurerAdapter;",
        "after": "",
        "kind": "remove_unused_imports",
        "bucket": "polishment"
      },
      {
        "general_idea": "Add new imports required for the updated security configuration.",
        "why_exists": "Missing imports cause compilation errors.",
        "before": "",
        "after": "import org.springframework.security.oauth2.server.resource.web.BearerTokenAuthenticationEntryPoint;",
        "kind": "add_required_imports",
        "bucket": "breaking"
      },
      {
        "general_idea": "Update constructor to inject JHipsterProperties instead of TokenProvider, CorsFilter, and SecurityProblemSupport.",
        "why_exists": "The old dependencies are no longer used in the new security configuration; injecting them causes compilation errors or unused dependency warnings.",
        "before": "public SecurityConfiguration(TokenProvider tokenProvider, CorsFilter corsFilter, SecurityProblemSupport problemSupport)",
        "after": "public SecurityConfiguration(JHipsterProperties jHipsterProperties)",
        "kind": "update_constructor",
        "bucket": "breaking"
      },
      {
        "general_idea": "Remove unused fields related to the old security configuration.",
        "why_exists": "Unused fields cause compilation warnings or errors in strict build environments.",
        "before": "private final TokenProvider tokenProvider;",
        "after": "",
        "kind": "remove_unused_fields",
        "bucket": "polishment"
      },
      {
        "general_idea": "Add new fields required for the updated security configuration.",
        "why_exists": "Missing fields cause compilation errors.",
        "before": "",
        "after": "private final JHipsterProperties jHipsterProperties;",
        "kind": "add_required_fields",
        "bucket": "breaking"
      },
      {
        "general_idea": "Add @Configuration annotation to the security configuration class.",
        "why_exists": "The @Configuration annotation is required for the class to be recognized as a Spring configuration class.",
        "before": "",
        "after": "@Configuration",
        "kind": "add_configuration_annotation",
        "bucket": "breaking"
      },
      {
        "general_idea": "Remove @Import annotation for SecurityProblemSupport as it is no longer used.",
        "why_exists": "The @Import annotation is no longer needed and causes compilation errors if the imported class is not found or used.",
        "before": "@Import(SecurityProblemSupport.class)",
        "after": "",
        "kind": "remove_unused_import_annotation",
        "bucket": "polishment"
      }
    ],
    "src/main/java/io/github/jhipster/sample/config/StaticResourcesWebConfiguration.java": [
      {
        "general_idea": "Refactor static resource location and path configuration to use a more granular and modern mapping strategy.",
        "why_exists": "",
        "before": "protected static final String[] RESOURCE_LOCATIONS = new String[] {\n        \"classpath:/static/app/\",\n        \"classpath:/static/content/\",\n        \"classpath:/static/i18n/\",\n    };\n    protected static final String[] RESOURCE_PATHS = new String[] { \"/app/*\", \"/content/*\", \"/i18n/*\" };",
        "after": "protected static final String[] RESOURCE_LOCATIONS = new String[] {\n        \"classpath:/static/\",\n        \"classpath:/static/content/\",\n        \"classpath:/static/i18n/\",\n    };\n    protected static final String[] RESOURCE_PATHS = new String[] {\n        \"/*.js\",\n        \"/*.css\",\n        \"/*.svg\",\n        \"/*.png\",\n        \"*.ico\",\n        \"/content/**\",\n        \"/i18n/*\",\n    };",
        "kind": "refactor_resource_mapping",
        "bucket": "polishment"
      }
    ],
    "src/main/java/io/github/jhipster/sample/config/WebConfigurer.java": [
      {
        "general_idea": "Replace javax.servlet imports with jakarta.servlet to align with Spring Boot 3.x and Jakarta EE 9+ namespace changes.",
        "why_exists": "javax.servlet classes are removed in Jakarta EE 9+/Spring Boot 3, causing compilation errors due to missing packages.",
        "before": "import javax.servlet.*;",
        "after": "import jakarta.servlet.*;",
        "kind": "javax_to_jakarta_namespace",
        "bucket": "breaking"
      },
      {
        "general_idea": "Remove unused import for MediaType which is no longer referenced in the class.",
        "why_exists": "",
        "before": "import org.springframework.http.MediaType;",
        "after": "",
        "kind": "remove_unused_import",
        "bucket": "polishment"
      },
      {
        "general_idea": "Remove unused import for UnsupportedEncodingException as the try-catch block handling it was removed.",
        "why_exists": "",
        "before": "import java.io.UnsupportedEncodingException;",
        "after": "",
        "kind": "remove_unused_import",
        "bucket": "polishment"
      },
      {
        "general_idea": "Remove unused import for java.util.* as specific collections are no longer used or handled differently.",
        "why_exists": "",
        "before": "import java.util.*;",
        "after": "",
        "kind": "remove_unused_import",
        "bucket": "polishment"
      },
      {
        "general_idea": "Use Java 16+ pattern matching for instanceof to simplify casting logic.",
        "why_exists": "",
        "before": "if (server instanceof ConfigurableServletWebServerFactory) {\n            ConfigurableServletWebServerFactory servletWebServer = (ConfigurableServletWebServerFactory) server;",
        "after": "if (server instanceof ConfigurableServletWebServerFactory servletWebServer) {",
        "kind": "pattern_matching_instanceof",
        "bucket": "polishment"
      },
      {
        "general_idea": "Simplify URL decoding by using StandardCharsets.UTF_8 directly, removing the try-catch for UnsupportedEncodingException which is unnecessary for UTF-8.",
        "why_exists": "",
        "before": "try {\n            fullExecutablePath = decode(this.getClass().getResource(\"\").getPath(), StandardCharsets.UTF_8.name());\n        } catch (UnsupportedEncodingException e) {\n            /* try without decoding if this ever happens */\n            fullExecutablePath = this.getClass().getResource(\"\").getPath();\n        }",
        "after": "String fullExecutablePath = decode(this.getClass().getResource(\"\").getPath(), StandardCharsets.UTF_8);",
        "kind": "simplify_url_decoding",
        "bucket": "polishment"
      },
      {
        "general_idea": "Update CORS configuration to check for allowedOriginPatterns in addition to allowedOrigins, supporting newer Spring Security/Spring MVC CORS APIs.",
        "why_exists": "",
        "before": "if (!CollectionUtils.isEmpty(config.getAllowedOrigins())) {",
        "after": "if (!CollectionUtils.isEmpty(config.getAllowedOrigins()) || !CollectionUtils.isEmpty(config.getAllowedOriginPatterns())) {",
        "kind": "update_cors_check",
        "bucket": "polishment"
      },
      {
        "general_idea": "Remove CORS registration for deprecated Swagger v2 endpoints (/v2/api-docs, /swagger-resources).",
        "why_exists": "",
        "before": "source.registerCorsConfiguration(\"/v2/api-docs\", config);\n            source.registerCorsConfiguration(\"/swagger-resources\", config);",
        "after": "",
        "kind": "remove_deprecated_swagger_cors",
        "bucket": "polishment"
      },
      {
        "general_idea": "Add CORS registration for Swagger UI v3 endpoint (/swagger-ui/**).",
        "why_exists": "",
        "before": "",
        "after": "source.registerCorsConfiguration(\"/swagger-ui/**\", config);",
        "kind": "add_swagger_ui_cors",
        "bucket": "polishment"
      }
    ]
  }
}