{
  "meta": {
    "repo": "mpalourdio/SpringBootTemplate",
    "stage": "J8->J11",
    "family": null,
    "sha_from": "fa30cf1021a1490b5341a61f03cde944957d1177",
    "sha_to": "466118e0a62aadc532459273c3b8e60b6bf85a39"
  },
  "by_file": {
    ".gitignore": [
      {
        "general_idea": "Add IDE-specific files to gitignore to prevent cluttering the repository with IntelliJ IDEA configuration files.",
        "why_exists": "",
        "before": "",
        "after": ".idea/\n*.iml",
        "kind": "add_ide_gitignore_entries",
        "bucket": "polishment"
      },
      {
        "general_idea": "Add local properties and logs directories to gitignore to exclude sensitive or transient runtime data from version control.",
        "why_exists": "",
        "before": "",
        "after": "properties/local.properties\nlogs",
        "kind": "add_local_data_gitignore_entries",
        "bucket": "polishment"
      }
    ],
    "LICENSE": [
      {
        "general_idea": "Update the copyright year range in the LICENSE file to reflect the current period of maintenance.",
        "why_exists": "",
        "before": "Copyright (c) 2013 mpalourdio",
        "after": "Copyright (c) 2016-2019 mpalourdio",
        "kind": "update_copyright_years",
        "bucket": "polishment"
      }
    ],
    "pom.xml": [
      {
        "general_idea": "Exclude JUnit Vintage engine to enforce JUnit 5 usage.",
        "why_exists": "JUnit 4 support is being dropped; without exclusion, tests might run on the legacy engine which may be deprecated or removed in future tooling.",
        "before": "",
        "after": "<exclusions>\n<exclusion>\n<groupId>org.junit.vintage</groupId>\n<artifactId>junit-vintage-engine</artifactId>\n</exclusion>\n</exclusions>",
        "kind": "exclude_junit_vintage",
        "bucket": "polishment"
      },
      {
        "general_idea": "Add Spring Cloud dependencies for config, eureka, and sleuth.",
        "why_exists": "",
        "before": "",
        "after": "<dependency>\n<groupId>org.springframework.cloud</groupId>\n<artifactId>spring-cloud-starter-config</artifactId>\n</dependency>\n<dependency>\n<groupId>org.springframework.cloud</groupId>\n<artifactId>spring-cloud-starter-netflix-eureka-client</artifactId>\n</dependency>\n<dependency>\n<groupId>org.springframework.cloud</groupId>\n<artifactId>spring-cloud-starter-sleuth</artifactId>\n</dependency>",
        "kind": "add_spring_cloud_deps",
        "bucket": "polishment"
      },
      {
        "general_idea": "Add Spring Boot Actuator dependency.",
        "why_exists": "",
        "before": "",
        "after": "<dependency>\n<groupId>org.springframework.boot</groupId>\n<artifactId>spring-boot-starter-actuator</artifactId>\n</dependency>",
        "kind": "add_actuator_dep",
        "bucket": "polishment"
      },
      {
        "general_idea": "Add Spring Security starter dependency.",
        "why_exists": "",
        "before": "",
        "after": "<dependency>\n<groupId>org.springframework.boot</groupId>\n<artifactId>spring-boot-starter-security</artifactId>\n</dependency>",
        "kind": "add_security_dep",
        "bucket": "polishment"
      },
      {
        "general_idea": "Add WebFlux starter dependency.",
        "why_exists": "",
        "before": "",
        "after": "<dependency>\n<groupId>org.springframework.boot</groupId>\n<artifactId>spring-boot-starter-webflux</artifactId>\n</dependency>",
        "kind": "add_webflux_dep",
        "bucket": "polishment"
      },
      {
        "general_idea": "Add ActiveMQ starter dependency.",
        "why_exists": "",
        "before": "",
        "after": "<dependency>\n<groupId>org.springframework.boot</groupId>\n<artifactId>spring-boot-starter-activemq</artifactId>\n</dependency>",
        "kind": "add_activemq_dep",
        "bucket": "polishment"
      },
      {
        "general_idea": "Add Lombok dependency.",
        "why_exists": "",
        "before": "",
        "after": "<dependency>\n<groupId>org.projectlombok</groupId>\n<artifactId>lombok</artifactId>\n<scope>provided</scope>\n</dependency>",
        "kind": "add_lombok_dep",
        "bucket": "polishment"
      },
      {
        "general_idea": "Add Apache Commons Text dependency.",
        "why_exists": "",
        "before": "",
        "after": "<dependency>\n<groupId>org.apache.commons</groupId>\n<artifactId>commons-text</artifactId>\n<version>${common-text.version}</version>\n</dependency>",
        "kind": "add_commons_text_dep",
        "bucket": "polishment"
      },
      {
        "general_idea": "Add Apache POI dependency.",
        "why_exists": "",
        "before": "",
        "after": "<dependency>\n<groupId>org.apache.poi</groupId>\n<artifactId>poi</artifactId>\n<version>${poi.version}</version>\n</dependency>",
        "kind": "add_poi_dep",
        "bucket": "polishment"
      },
      {
        "general_idea": "Add Apache HttpClient dependency.",
        "why_exists": "",
        "before": "",
        "after": "<dependency>\n<groupId>org.apache.httpcomponents</groupId>\n<artifactId>httpclient</artifactId>\n</dependency>",
        "kind": "add_httpclient_dep",
        "bucket": "polishment"
      },
      {
        "general_idea": "Add Commons Codec dependency.",
        "why_exists": "",
        "before": "",
        "after": "<dependency>\n<groupId>commons-codec</groupId>\n<artifactId>commons-codec</artifactId>\n</dependency>",
        "kind": "add_commons_codec_dep",
        "bucket": "polishment"
      },
      {
        "general_idea": "Add Apache Commons Lang3 dependency.",
        "why_exists": "",
        "before": "",
        "after": "<dependency>\n<groupId>org.apache.commons</groupId>\n<artifactId>commons-lang3</artifactId>\n</dependency>",
        "kind": "add_commons_lang3_dep",
        "bucket": "polishment"
      },
      {
        "general_idea": "Add Spring Boot Configuration Processor dependency.",
        "why_exists": "",
        "before": "",
        "after": "<dependency>\n<groupId>org.springframework.boot</groupId>\n<artifactId>spring-boot-configuration-processor</artifactId>\n<optional>true</optional>\n</dependency>",
        "kind": "add_config_processor_dep",
        "bucket": "polishment"
      },
      {
        "general_idea": "Add H2 database dependency for tests.",
        "why_exists": "",
        "before": "",
        "after": "<dependency>\n<groupId>com.h2database</groupId>\n<artifactId>h2</artifactId>\n<scope>test</scope>\n</dependency>",
        "kind": "add_h2_test_dep",
        "bucket": "polishment"
      },
      {
        "general_idea": "Add Reactor Test dependency for tests.",
        "why_exists": "",
        "before": "",
        "after": "<dependency>\n<groupId>io.projectreactor</groupId>\n<artifactId>reactor-test</artifactId>\n<scope>test</scope>\n</dependency>",
        "kind": "add_reactor_test_dep",
        "bucket": "polishment"
      },
      {
        "general_idea": "Add Spring Security Test dependency for tests.",
        "why_exists": "",
        "before": "",
        "after": "<dependency>\n<groupId>org.springframework.security</groupId>\n<artifactId>spring-security-test</artifactId>\n<scope>test</scope>\n</dependency>",
        "kind": "add_security_test_dep",
        "bucket": "polishment"
      },
      {
        "general_idea": "Add Spring Cloud dependency management BOM.",
        "why_exists": "",
        "before": "",
        "after": "<dependencyManagement>\n<dependencies>\n<dependency>\n<groupId>org.springframework.cloud</groupId>\n<artifactId>spring-cloud-dependencies</artifactId>\n<version>${spring-cloud.version}</version>\n<type>pom</type>\n<scope>import</scope>\n</dependency>\n</dependencies>\n</dependencyManagement>",
        "kind": "add_spring_cloud_bom",
        "bucket": "polishment"
      },
      {
        "general_idea": "Add Spring Snapshots and Milestones repositories.",
        "why_exists": "",
        "before": "",
        "after": "<repositories>\n<repository>\n<id>spring-snapshots</id>\n<name>Spring Snapshots</name>\n<url>https://repo.spring.io/snapshot</url>\n<snapshots>\n<enabled>true</enabled>\n</snapshots>\n</repository>\n<repository>\n<id>spring-milestones</id>\n<name>Spring Milestones</name>\n<url>https://repo.spring.io/milestone</url>\n</repository>\n</repositories>",
        "kind": "add_spring_repos",
        "bucket": "polishment"
      },
      {
        "general_idea": "Add Spring Snapshots and Milestones plugin repositories.",
        "why_exists": "",
        "before": "",
        "after": "<pluginRepositories>\n<pluginRepository>\n<id>spring-snapshots</id>\n<name>Spring Snapshots</name>\n<url>https://repo.spring.io/snapshot</url>\n<snapshots>\n<enabled>true</enabled>\n</snapshots>\n</pluginRepository>\n<pluginRepository>\n<id>spring-milestones</id>\n<name>Spring Milestones</name>\n<url>https://repo.spring.io/milestone</url>\n</pluginRepository>\n</pluginRepositories>",
        "kind": "add_spring_plugin_repos",
        "bucket": "polishment"
      },
      {
        "general_idea": "Configure Maven Checkstyle plugin.",
        "why_exists": "",
        "before": "",
        "after": "<plugin>\n<groupId>org.apache.maven.plugins</groupId>\n<artifactId>maven-checkstyle-plugin</artifactId>\n<version>${maven-checkstyle-plugin.version}</version>\n<dependencies>\n<dependency>\n<groupId>com.puppycrawl.tools</groupId>\n<artifactId>checkstyle</artifactId>\n<version>${checkstyle.version}</version>\n</dependency>\n</dependencies>\n<executions>\n<execution>\n<id>validate</id>\n<phase>validate</phase>\n<configuration>\n<configLocation>${maven-checkstyle-plugin.configLocation}</configLocation>\n<encoding>UTF-8</encoding>\n<consoleOutput>true</consoleOutput>\n<failsOnError>true</failsOnError>\n</configuration>\n<goals>\n<goal>check</goal>\n</goals>\n</execution>\n</executions>\n</plugin>",
        "kind": "add_checkstyle_plugin",
        "bucket": "polishment"
      },
      {
        "general_idea": "Configure Maven Release plugin.",
        "why_exists": "",
        "before": "",
        "after": "<plugin>\n<groupId>org.apache.maven.plugins</groupId>\n<artifactId>maven-release-plugin</artifactId>\n<version>${maven-release-plugin.version}</version>\n<configuration>\n<pushChanges>false</pushChanges>\n<arguments>-Dmaven.javadoc.skip=true</arguments>\n</configuration>\n</plugin>",
        "kind": "add_release_plugin",
        "bucket": "polishment"
      },
      {
        "general_idea": "Configure Spring Boot Maven plugin to create executable jar.",
        "why_exists": "",
        "before": "<plugin>\n<groupId>org.springframework.boot</groupId>\n<artifactId>spring-boot-maven-plugin</artifactId>\n</plugin>",
        "after": "<plugin>\n<groupId>org.springframework.boot</groupId>\n<artifactId>spring-boot-maven-plugin</artifactId>\n<executions>\n<execution>\n<id>repackage</id>\n<configuration>\n<executable>true</executable>\n</configuration>\n</execution>\n</executions>\n</plugin>",
        "kind": "configure_boot_plugin",
        "bucket": "polishment"
      },
      {
        "general_idea": "Update project coordinates (groupId, artifactId, name, url).",
        "why_exists": "",
        "before": "<groupId>com.mpalourdio.com</groupId>\n<artifactId>first</artifactId>\n<name>ben</name>\n<url>http://maven.apache.org</url>",
        "after": "<groupId>com.mpalourdio.projects</groupId>\n<artifactId>springboottemplate</artifactId>\n<name>Spring Boot Template</name>\n<url>https://github.com/mpalourdio/SpringBootTemplate</url>",
        "kind": "update_project_coords",
        "bucket": "polishment"
      },
      {
        "general_idea": "Add SCM configuration.",
        "why_exists": "",
        "before": "",
        "after": "<scm>\n<developerConnection>scm:git:git@github.com:mpalourdio/SpringBootTemplate.git</developerConnection>\n<tag>HEAD</tag>\n</scm>",
        "kind": "add_scm_config",
        "bucket": "polishment"
      },
      {
        "general_idea": "Add relativePath to parent POM.",
        "why_exists": "",
        "before": "",
        "after": "<relativePath/>",
        "kind": "add_parent_relative_path",
        "bucket": "polishment"
      },
      {
        "general_idea": "Add reporting output encoding property.",
        "why_exists": "",
        "before": "",
        "after": "<project.reporting.outputEncoding>UTF-8</project.reporting.outputEncoding>",
        "kind": "add_reporting_encoding",
        "bucket": "polishment"
      },
      {
        "general_idea": "Add Spring Cloud version property.",
        "why_exists": "",
        "before": "",
        "after": "<spring-cloud.version>Hoxton.SR3</spring-cloud.version>",
        "kind": "add_spring_cloud_version_prop",
        "bucket": "polishment"
      },
      {
        "general_idea": "Add version properties for dependencies and plugins.",
        "why_exists": "",
        "before": "",
        "after": "<common-text.version>1.8</common-text.version>\n<poi.version>4.1.0</poi.version>\n<maven-release-plugin.version>2.5.3</maven-release-plugin.version>\n<maven-checkstyle-plugin.version>3.1.1</maven-checkstyle-plugin.version>\n<checkstyle.version>8.29</checkstyle.version>\n<maven-checkstyle-plugin.configLocation>https://raw.githubusercontent.com/mpalourdio/configuration/master/checkstyle.xml</maven-checkstyle-plugin.configLocation>",
        "kind": "add_version_properties",
        "bucket": "polishment"
      },
      {
        "general_idea": "Add finalName configuration to build.",
        "why_exists": "",
        "before": "",
        "after": "<finalName>${project.artifactId}</finalName>",
        "kind": "add_final_name",
        "bucket": "polishment"
      }
    ]
  }
}