{
  "meta": {
    "repo": "felix-murcia/OAuth2Server",
    "stage": "J11->J17",
    "family": "spring-boot-2",
    "sha_from": "44377a62b85ad4079b7757a0a908ae9e70daadc2",
    "sha_to": "48b8091f8bc334fd9e4890dd9e51f8b014556403"
  },
  "by_file": {
    "Dockerfile": [
      {
        "general_idea": "Replace CMD with ENTRYPOINT to allow Kubernetes to override arguments while keeping the Java execution fixed.",
        "why_exists": "",
        "before": "CMD [\"java\", \"-jar\", \"/app/app.jar\"]",
        "after": "ENTRYPOINT [\"java\", \"-jar\", \"/app/app.jar\"]",
        "kind": "docker_entrypoint_change",
        "bucket": "polishment"
      }
    ],
    "docker-compose.yml": [
      {
        "general_idea": "Remove the deprecated 'version' field from docker-compose.yml as it is no longer required in modern Compose specifications.",
        "why_exists": "",
        "before": "version: \"3.8\"",
        "after": "",
        "kind": "remove_deprecated_compose_version",
        "bucket": "polishment"
      },
      {
        "general_idea": "Switch from using a pre-built image to building the service locally to support the new Java 17 environment.",
        "why_exists": "",
        "before": "image: oauth2-server:latest",
        "after": "build: .",
        "kind": "switch_to_local_build",
        "bucket": "polishment"
      },
      {
        "general_idea": "Update the image tag to a specific development version for the new build context.",
        "why_exists": "",
        "before": "image: oauth2-server:latest",
        "after": "image: felixmurcia/oauth2server:dev",
        "kind": "update_image_tag",
        "bucket": "polishment"
      },
      {
        "general_idea": "Change the volume mount path to match the new container structure or host directory layout.",
        "why_exists": "",
        "before": "- ./data:/data",
        "after": "- /home/jetson/oauth2db:/app/data",
        "kind": "update_volume_mount",
        "bucket": "polishment"
      },
      {
        "general_idea": "Add an explicit command to run a specific startup script for the development environment.",
        "why_exists": "",
        "before": "",
        "after": "command: [\"/app/run-dev.sh\"]",
        "kind": "add_startup_command",
        "bucket": "polishment"
      }
    ],
    "k8s/deployment.yaml": [
      {
        "general_idea": "Add JWT_AUDIENCE environment variable to the Kubernetes deployment configuration.",
        "why_exists": "",
        "before": "",
        "after": "- name: JWT_AUDIENCE\n              valueFrom:\n                secretKeyRef:\n                  name: oauth2-secrets\n                  key: oauth-audience",
        "kind": "add_env_var",
        "bucket": "polishment"
      }
    ],
    "pom.xml": [
      {
        "general_idea": "Add Spring Security OAuth2 Authorization Server dependency for new OAuth2 features.",
        "why_exists": "",
        "before": "",
        "after": "<artifactId>spring-security-oauth2-authorization-server</artifactId>",
        "kind": "add_oauth2_auth_server",
        "bucket": "polishment"
      },
      {
        "general_idea": "Add springdoc.version property to manage OpenAPI dependency version.",
        "why_exists": "",
        "before": "",
        "after": "<springdoc.version>2.5.0</springdoc.version>",
        "kind": "add_property",
        "bucket": "polishment"
      },
      {
        "general_idea": "Update ModelMapper version to 3.2.0 for compatibility and bug fixes.",
        "why_exists": "",
        "before": "<version>3.1.1</version>",
        "after": "<version>3.2.0</version>",
        "kind": "update_dependency_version",
        "bucket": "polishment"
      },
      {
        "general_idea": "Remove explicit Jackson Databind dependency, relying on Spring Boot BOM management.",
        "why_exists": "",
        "before": "<artifactId>jackson-databind</artifactId>",
        "after": "",
        "kind": "remove_dependency",
        "bucket": "polishment"
      },
      {
        "general_idea": "Remove explicit Swagger UI WebJar dependency, replaced by Springdoc UI.",
        "why_exists": "",
        "before": "<artifactId>swagger-ui</artifactId>",
        "after": "",
        "kind": "remove_dependency",
        "bucket": "polishment"
      },
      {
        "general_idea": "Add Spring Security Test dependency for testing security configurations.",
        "why_exists": "",
        "before": "",
        "after": "<artifactId>spring-security-test</artifactId>",
        "kind": "add_test_dependency",
        "bucket": "polishment"
      },
      {
        "general_idea": "Update Flyway Core version to 10.7.1 for compatibility with newer database drivers and Spring Boot 3.",
        "why_exists": "",
        "before": "",
        "after": "<version>10.7.1</version>",
        "kind": "update_dependency_version",
        "bucket": "polishment"
      },
      {
        "general_idea": "Remove H2 database dependency, likely switching to a different database or managed profile.",
        "why_exists": "",
        "before": "<artifactId>h2</artifactId>",
        "after": "",
        "kind": "remove_dependency",
        "bucket": "polishment"
      },
      {
        "general_idea": "Remove maven-surefire-plugin configuration that skipped tests, enabling test execution.",
        "why_exists": "",
        "before": "<skipTests>true</skipTests>",
        "after": "",
        "kind": "enable_tests",
        "bucket": "polishment"
      },
      {
        "general_idea": "Configure Spring Boot Maven Plugin to exclude Lombok from the repackaged jar.",
        "why_exists": "",
        "before": "",
        "after": "<exclude><groupId>org.projectlombok</groupId>",
        "kind": "configure_plugin_exclusion",
        "bucket": "polishment"
      }
    ],
    "scripts/run-dev.sh": [
      {
        "general_idea": "Migrate Spring profile activation from environment variable to JVM system property.",
        "why_exists": "",
        "before": "export SPRING_PROFILES_ACTIVE=dev\njava -jar /app/app.jar",
        "after": "java -Dspring.profiles.active=dev -Dserver.address=0.0.0.0 -jar /app/app.jar",
        "kind": "migrate_profile_activation_to_jvm_arg",
        "bucket": "polishment"
      },
      {
        "general_idea": "Explicitly bind the server to all network interfaces via JVM system property.",
        "why_exists": "",
        "before": "java -jar /app/app.jar",
        "after": "java -Dspring.profiles.active=dev -Dserver.address=0.0.0.0 -jar /app/app.jar",
        "kind": "add_server_address_binding",
        "bucket": "polishment"
      }
    ],
    "src/main/java/com/oauth/rest/config/WebConfig.java": [
      {
        "general_idea": "Remove unused import of org.springframework.core.annotation.Order",
        "why_exists": "",
        "before": "import org.springframework.core.annotation.Order;",
        "after": "",
        "kind": "remove_unused_import",
        "bucket": "polishment"
      },
      {
        "general_idea": "Remove @Order annotation from bean method",
        "why_exists": "",
        "before": "@Order(1)\n    public CorsConfigurationSource corsConfigurationSource()",
        "after": "public CorsConfigurationSource corsConfigurationSource()",
        "kind": "remove_annotation",
        "bucket": "polishment"
      }
    ],
    "src/main/java/com/oauth/rest/model/UserEntity.java": [
      {
        "general_idea": "Add a new 'application' field to the UserEntity model.",
        "why_exists": "",
        "before": "",
        "after": "@Column(name = \"app\")\nprivate String application;",
        "kind": "add_field",
        "bucket": "polishment"
      },
      {
        "general_idea": "Add getter and setter methods for the new 'application' field.",
        "why_exists": "",
        "before": "",
        "after": "public String getApplication() {\n    return application;\n}\n\npublic void setApplication(String application) {\n    this.application = application;\n}",
        "kind": "add_accessors",
        "bucket": "polishment"
      },
      {
        "general_idea": "Reformat constructor parameter alignment for consistency.",
        "why_exists": "",
        "before": "                      Set<UserRole> roles, LocalDateTime createdAt, LocalDateTime lastPasswordChangeAt) {",
        "after": "            Set<UserRole> roles, LocalDateTime createdAt, LocalDateTime lastPasswordChangeAt) {",
        "kind": "code_formatting",
        "bucket": "polishment"
      }
    ],
    "src/main/java/com/oauth/rest/security/oauth2/OAuth2ResourceServer.java": [
      {
        "general_idea": "Update Swagger API docs endpoint path from v2 to v3.",
        "why_exists": "",
        "before": "\"/v2/api-docs\"",
        "after": "\"/v3/api-docs\"",
        "kind": "update_dependency_version",
        "bucket": "polishment"
      }
    ]
  }
}