{
  "slug": "mehmandarov_5-features-talk-demo__J17toJ21",
  "stage": {
    "repo": "mehmandarov/5-features-talk-demo",
    "sha_to": "2ac2413958cc3e478fc50ed1e61fad05e919c1eb",
    "next_version_commit": "2ac2413958cc3e478fc50ed1e61fad05e919c1eb",
    "jv_from": 17,
    "jv_to": 21,
    "lineage_versions": [
      17,
      21
    ]
  },
  "probes": [
    {
      "distance_back": 20,
      "sha": "cf30af8ac3e814eba1661bafd0157805bca5d41d",
      "compile_ok": true,
      "pass": 0,
      "fail": 0,
      "pass_rate": 0.0,
      "note": "test_rc=0"
    },
    {
      "distance_back": 50,
      "note": "history_too_short"
    }
  ],
  "selected": null,
  "skipped_reason": "no_candidate_met_bar"
}