{
  "slug": "Pamuditha1_overleaf-rnd__J8toJ21",
  "stage": {
    "repo": "Pamuditha1/overleaf-rnd",
    "sha_to": "3e81e212f38e3af35fee9f3578ac97201ec155c7",
    "next_version_commit": "3e81e212f38e3af35fee9f3578ac97201ec155c7",
    "jv_from": 8,
    "jv_to": 21,
    "lineage_versions": [
      8,
      21
    ]
  },
  "probes": [
    {
      "distance_back": 20,
      "sha": "15cdec642d3751a4df16c52bbcf863b278c1863c",
      "compile_ok": false,
      "pass": 0,
      "fail": 0,
      "pass_rate": 0.0,
      "note": "compile_rc=1"
    },
    {
      "distance_back": 50,
      "sha": "9075c82b882c6f9b1a45d85004853d5d73b1a904",
      "compile_ok": false,
      "pass": 0,
      "fail": 0,
      "pass_rate": 0.0,
      "note": "compile_rc=1"
    },
    {
      "distance_back": 100,
      "sha": "a0d2d30b489b8de7c5c272e6b1e2ad2675d37680",
      "compile_ok": false,
      "pass": 0,
      "fail": 0,
      "pass_rate": 0.0,
      "note": "compile_rc=1"
    },
    {
      "distance_back": 200,
      "sha": "49dc94192aef0c1a6195ff18e1327651aa19e1f6",
      "compile_ok": false,
      "pass": 0,
      "fail": 0,
      "pass_rate": 0.0,
      "note": "compile_rc=1"
    }
  ],
  "selected": null,
  "skipped_reason": "no_candidate_met_bar"
}