{
  "slug": "tonigarioliver_MicroservicesApp__J17toJ21",
  "stage": {
    "repo": "tonigarioliver/MicroservicesApp",
    "sha_to": "06a1c2fae9174cb74115a1d004649e496377e3ce",
    "next_version_commit": "06a1c2fae9174cb74115a1d004649e496377e3ce",
    "jv_from": 17,
    "jv_to": 21,
    "lineage_versions": [
      17,
      21
    ]
  },
  "probes": [
    {
      "distance_back": 20,
      "sha": "2d2c445c3d0642cda51d0bc707473f2c960e6b91",
      "compile_ok": true,
      "pass": 1,
      "fail": 0,
      "pass_rate": 1.0,
      "note": "test_rc=0"
    }
  ],
  "selected": {
    "repo": "tonigarioliver/MicroservicesApp",
    "sha_from": "2d2c445c3d0642cda51d0bc707473f2c960e6b91",
    "sha_to": "06a1c2fae9174cb74115a1d004649e496377e3ce",
    "jv_from": 17,
    "jv_to": 21,
    "next_version_commit": "06a1c2fae9174cb74115a1d004649e496377e3ce",
    "commits_back": 20,
    "pre_pass_count": 1,
    "pre_fail_count": 0,
    "pass_rate": 1.0,
    "probes_tried": 1
  },
  "skipped_reason": null
}