{
  "stage": {
    "repo": "AliHassan104/question-bank",
    "sha_from": "bdee64f03dce9f84c33ed8573c3a45c7ed1b9061",
    "sha_to": "1187c5bbb8d4ef2afaa46726377ac3b3dc28a1ac",
    "i0_status": "recipe_fail",
    "i0_pass": false
  },
  "started_at": 1779763257.7271702,
  "steps": [
    {
      "step": "java8_to_java11",
      "jdk": 11,
      "recipe_count": 1,
      "recipe_rc": 1,
      "recipe_ok": false,
      "recipe_log_tail": "GradleModule.java:63)\n[ERROR]   org.openrewrite.maven.internal.MavenPomDownloader.download(MavenPomDownloader.java:638)\n[ERROR]   org.openrewrite.maven.tree.ResolvedPom.resolveDependencies(ResolvedPom.java:1050)\n[ERROR]   org.openrewrite.maven.tree.ResolvedPom.resolveDependencies(ResolvedPom.java:969)\n[ERROR]   org.openrewrite.maven.tree.MavenResolutionResult.resolveDependencies(MavenResolutionResult.java:189)\n[ERROR] -> [Help 1]\n[ERROR] \n[ERROR] To see the full stack trace of the errors, re-run Maven with the -e switch.\n[ERROR] Re-run Maven using the -X switch to enable full debug logging.\n[ERROR] \n[ERROR] For more information about the errors and possible solutions, please read the following articles:\n[ERROR] [Help 1] http://cwiki.apache.org/confluence/display/MAVEN/MojoFailureException\n"
    }
  ],
  "aborted_at": "java8_to_java11",
  "finished_at": 1779763287.6301928,
  "wall_s": 29.9,
  "final_status": "FAIL_at_java8_to_java11"
}