{
  "stage": {
    "repo": "genesis177/java-explore-with-me",
    "sha_from": "4cbb792c732ef234e16aa00302b47be154866253",
    "sha_to": "50a0f43323ff978b3457c18a07651d3523764209",
    "jv_from": 11,
    "jv_to": 21,
    "i0_status": "FULL_PASS",
    "i0_pass": true
  },
  "started_at": 1779764326.6502345,
  "steps": [
    {
      "step": "upgrade_plugins_for_java17",
      "jdk": 11,
      "recipe_count": 1,
      "recipe_rc": 0,
      "recipe_ok": true,
      "build_rc": 0,
      "build_ok": true
    },
    {
      "step": "upgrade_build_to_java17",
      "jdk": 17,
      "recipe_count": 1,
      "recipe_rc": 0,
      "recipe_ok": true,
      "build_rc": 0,
      "build_ok": true
    },
    {
      "step": "java17_transforms",
      "jdk": 17,
      "recipe_count": 16,
      "recipe_rc": 0,
      "recipe_ok": true,
      "build_rc": 0,
      "build_ok": true
    },
    {
      "step": "upgrade_plugins_for_java21",
      "jdk": 17,
      "recipe_count": 1,
      "recipe_rc": 0,
      "recipe_ok": true,
      "build_rc": 0,
      "build_ok": true
    },
    {
      "step": "upgrade_build_to_java21",
      "jdk": 21,
      "recipe_count": 1,
      "recipe_rc": 0,
      "recipe_ok": true,
      "build_rc": 0,
      "build_ok": true
    },
    {
      "step": "java21_transforms",
      "jdk": 21,
      "recipe_count": 8,
      "recipe_rc": 0,
      "recipe_ok": true,
      "build_rc": 0,
      "build_ok": true
    }
  ],
  "finished_at": 1779764437.3372173,
  "wall_s": 110.7,
  "final_status": "PASS"
}