{
  "meta": {
    "repo": "Biershoot/API_Notificaciones_Tiempo_Real",
    "stage": "J17->J21",
    "sha_from": "2d952f3aa12c3389de5e8a90a40b2183b1d0e4a9",
    "recipe": "UpgradeToJava21+UpgradeSpringBoot_3_3+AddJaxbDependenciesWithRuntime+UpgradeJaCoCo"
  },
  "by_file": {
    "pom.xml": [
      {
        "general_idea": "Update the Java version property from 17 to 21 to target the new JDK.",
        "why_exists": "Without this change, the build targets Java 17, failing to leverage Java 21 features and potentially causing incompatibility with libraries requiring Java 21.",
        "before": "<java.version>17</java.version>",
        "after": "<java.version>21</java.version>",
        "kind": "update_java_version_property",
        "bucket": "breaking"
      },
      {
        "general_idea": "Configure the Maven compiler plugin to use the release flag matching the java.version property.",
        "why_exists": "Without this change, the compiler may not enforce the target bytecode version correctly, leading to potential runtime issues on Java 21 or failure to use Java 21-specific APIs if the source level isn't aligned.",
        "before": "",
        "after": "<release>${java.version}</release>",
        "kind": "add_compiler_release_flag",
        "bucket": "breaking"
      }
    ]
  }
}